shaka_streamer-1.2.1.data/scripts/shaka-streamer
streamer/__init__.py
streamer/autodetect.py
streamer/bitrate_configuration.py
streamer/configuration.py
streamer/controller_node.py
streamer/external_command_node.py
streamer/input_configuration.py
streamer/m3u8_concater.py
streamer/min_versions.py
streamer/node_base.py
streamer/output_stream.py
streamer/packager_node.py
streamer/periodconcat_node.py
streamer/pipe.py
streamer/pipeline_configuration.py
streamer/proxy_node.py
streamer/subprocessWindowsPatch.py
streamer/transcoder_node.py
streamer/util.py
shaka_streamer-1.2.1.dist-info/LICENSE
shaka_streamer-1.2.1.dist-info/METADATA
shaka_streamer-1.2.1.dist-info/WHEEL
shaka_streamer-1.2.1.dist-info/top_level.txt
shaka_streamer-1.2.1.dist-info/RECORD
