Metadata-Version: 2.2
Name: shaka-streamer
Version: 1.2.1
Summary: A simple config-file based approach to streaming media.
Home-page: https://github.com/shaka-project/shaka-streamer
Author: Google
Classifier: Programming Language :: Python :: 3
Classifier: License :: OSI Approved :: Apache Software License
Classifier: Operating System :: POSIX :: Linux
Classifier: Operating System :: MacOS :: MacOS X
Classifier: Operating System :: Microsoft :: Windows
Requires-Python: >=3.9
License-File: LICENSE
Requires-Dist: pywin32>=308; platform_system == "Windows"
Requires-Dist: pyyaml<7,>=6
Requires-Dist: setproctitle<2,>=1
Requires-Dist: typing_extensions<5,>=4
Dynamic: author
Dynamic: classifier
Dynamic: description
Dynamic: description-content-type
Dynamic: home-page
Dynamic: requires-dist
Dynamic: requires-python
Dynamic: summary
